handle_logointro/__init__.py
handle_logointro/api.py
handle_logointro/application.py
handle_logointro/get_event.py
handle_logointro/handler.py
handle_logointro/sample_events.py
handle_logointro/controllers/base_controller.py
handle_logointro/controllers/handle_logointro_controller.py
handle_logointro/factories/base_factory.py
handle_logointro/factories/factory.py
handle_logointro/infra/aws_request.py
handle_logointro/infra/rest.py
handle_logointro/infra/script.py
handle_logointro/infra/handle_logointro/handle_logointro.py
handle_logointro/models/ad.py
handle_logointro/models/logointro.py
handle_logointro/models/page.py
handle_logointro/models/request.py
handle_logointro/models/response.py
handle_logointro/models/saved_file.py
handle_logointro/models/video.py
handle_logointro/services/base_service.py
handle_logointro/services/handle_logointro_service.py
handle_logointro/services/speech_service.py
handle_logointro/services/text_utils_service.py
handle_logointro/services/time_service.py
handle_logointro/utils/file.py
handle_logointro/utils/helpers.py
handle_logointro/utils/html.py
handle_logointro/utils/json.py
handle_logointro/utils/lambda_helpers.py
handle_logointro/utils/markdown.py
handle_logointro/utils/service_helper.py
handle_logointro/utils/string_utils.py
handle_logointro/utils/text.py
handle_logointro/utils/time.py
handle_logointro/utils/url.py
handle_logointro/utils/video.py
video_bot_handle_logointro-0.0.1.dist-info/LICENSE
video_bot_handle_logointro-0.0.1.dist-info/METADATA
video_bot_handle_logointro-0.0.1.dist-info/WHEEL
video_bot_handle_logointro-0.0.1.dist-info/top_level.txt
video_bot_handle_logointro-0.0.1.dist-info/RECORD
