Metadata-Version: 2.1
Name: video-bot-handle-logointro
Version: 0.0.1
Summary: Handle Logo Intro module
Author-email: Bruno de Paula <bruno.bert.jj@gmail.com>
License: MIT License
Project-URL: Homepage, https://github.com/bruno-bert/microservice-handle-logointro
Keywords: image,thumb
Classifier: Programming Language :: Python :: 3
Classifier: License :: OSI Approved :: MIT License
Classifier: Operating System :: OS Independent
Requires-Python: >=3.7
License-File: LICENSE
